composabl_api_dev-0.19.1.dist-info/METADATA
composabl_api_dev-0.19.1.dist-info/RECORD
composabl_api_dev-0.19.1.dist-info/top_level.txt
composabl_api_dev-0.19.1.dist-info/WHEEL
composabl_api/common.cpython-311-aarch64-linux-gnu.so
composabl_api/__init__.cpython-311-aarch64-linux-gnu.so
composabl_api/nocode/__init__.cpython-311-aarch64-linux-gnu.so
composabl_api/nocode/main.cpython-311-aarch64-linux-gnu.so
composabl_api/controller/service.cpython-311-aarch64-linux-gnu.so
composabl_api/controller/__init__.cpython-311-aarch64-linux-gnu.so
composabl_api/controller/main.cpython-311-aarch64-linux-gnu.so
composabl_api/controller/job_status_enum.cpython-311-aarch64-linux-gnu.so
composabl_api/util/logger.cpython-311-aarch64-linux-gnu.so
composabl_api/util/singleton.cpython-311-aarch64-linux-gnu.so
composabl_api/util/token.cpython-311-aarch64-linux-gnu.so
composabl_api/util/__init__.cpython-311-aarch64-linux-gnu.so
