Metadata-Version: 2.4
Name: composabl-api-dev
Version: 0.19.1
Summary: the Composabl API
Author-email: Hunter Park <hunter@composabl.com>
Requires-Python: >=3.10, <3.13
Requires-Dist: cython
Requires-Dist: ruff
Requires-Dist: simple-term-menu
Requires-Dist: aiohttp
Requires-Dist: httpretty==1.0.5
Requires-Dist: pytest-asyncio
Requires-Dist: pre-commit
Dynamic: description
Dynamic: description-content-type
Dynamic: requires-python
